{
    "demo_data_generation": false,
    "auxiliary_model": null,
    "community_embedding_model_name": "primera_clip",
    "article_embedding_model_name": "longformer",
    "community_aggregation_type": "influence_passivity",
    "logger_path": "/home/ataylor2/processing_covid_tweets/Thunder/Logs",
    "best_model_output_path": "/home/ataylor2/processing_covid_tweets/Thunder/Best_Models",
    "cached_datapath": "/home/ataylor2/processing_covid_tweets/Thunder/cached_data",
    "info_pathway_instances_datapath": "/home/ataylor2/processing_covid_tweets/Thunder/Information_Pathways/top90_IP_Comm/",
    "training_instances_filename" : "window_1_instances.pkl",
    "evaluation_instances_filename" : "window_2_instances.pkl",
    "comm_feats_datapath": "/home/ataylor2/processing_covid_tweets/Thunder/community_embeddings",
    "training_comm_features" : "window_0_primera_clip",
    "eval_comm_features" : "window_1_primera_clip",
    "article_features_datapath": "/home/ataylor2/processing_covid_tweets/Thunder/article_embeddings",
    "training_article_features" : "window_1_article_embeddings.pkl",
    "eval_article_features" : "window_2_article_embeddings.pkl",
    "subgraph_max_size": 25,
    "subgraph_min_size": 4,
    "hidden_layer_size": 256,
    "ablation_type": "comm_article",
    "embedding_dim": 512,
    "cuda_device": 1
}